gocd_tools/__init__.py
gocd_tools/_version.py
gocd_tools/config.py
gocd_tools/defaults.py
gocd_tools/io.py
gocd_tools/plugin.py
gocd_tools/secrets.py
gocd_tools/server.py
gocd_tools/utils.py
gocd_tools/cli/__init__.py
gocd_tools/cli/cli.py
gocd_tools/cli/defaults.py
gocd_tools/cli/run.py
gocd_tools/cli/secrets.py
gocd_tools/cli/server.py
gocd_tools/cli/setup.py
gocd_tools-0.0.1.dist-info/licenses/LICENSE
gocd_tools-0.0.1.dist-info/METADATA
gocd_tools-0.0.1.dist-info/WHEEL
gocd_tools-0.0.1.dist-info/entry_points.txt
gocd_tools-0.0.1.dist-info/top_level.txt
gocd_tools-0.0.1.dist-info/RECORD
